setup.py
redcelery/__init__.py
redcelery.egg-info/PKG-INFO
redcelery.egg-info/SOURCES.txt
redcelery.egg-info/dependency_links.txt
redcelery.egg-info/pbr.json
redcelery.egg-info/requires.txt
redcelery.egg-info/top_level.txt