Metadata-Version: 1.0
Name: redcelery
Version: 3.1.18
Summary: Patches for celery which attempt to mitigate issues with its use of redis connections causing workers to hang
Home-page: https://github.com/reversefold/redcelery
Author: Justin Patrin
Author-email: papercrane@reversefold.com
License: MIT
Platform: UNKNOWN
